.DS_Store
dotmailer/__init__.py
dotmailer/account.py
dotmailer/address_books.py
dotmailer/campaigns.py
dotmailer/connection.py
dotmailer/constants.py
dotmailer/contact_data_fields.py
dotmailer/contacts.py
dotmailer/documents.py
dotmailer/exceptions.py
dotmailer/images.py
dotmailer/program_enrolments.py
dotmailer/programs.py
dotmailer/segments.py
dotmailer/survey_fields.py
dotmailer/survey_page.py
dotmailer/surveys.py
dotmailer/templates.py
dotmailer/transactional_email.py
dotmailer/transactional_emails.py
dotmailer-0.4.2.dist-info/DESCRIPTION.rst
dotmailer-0.4.2.dist-info/METADATA
dotmailer-0.4.2.dist-info/RECORD
dotmailer-0.4.2.dist-info/WHEEL
dotmailer-0.4.2.dist-info/metadata.json
dotmailer-0.4.2.dist-info/top_level.txt
tests/__init__.py
tests/conftest.py
tests/test_account.py
tests/test_address_book.py
tests/test_contact_data_fields.py
tests/test_contacts.py
tests/test_program_enrolments.py
tests/test_programs.py
tests/test_templates.py
tests/test_transaction_emails.py
