Metadata-Version: 2.0
Name: dotmailer
Version: 0.4.2
Summary: DotMailer API wrapper
Home-page: https://github.com/Mr-F/dotmailer
Author: Keith M Franklin
Author-email: test@test.com
License: MIT
Keywords: python dotmailer api
Platform: UNKNOWN
Classifier: Development Status :: 2 - Pre-Alpha
Classifier: Intended Audience :: Developers
Classifier: License :: OSI Approved :: MIT License
Classifier: Natural Language :: English
Classifier: Operating System :: OS Independent
Classifier: Programming Language :: Python
Classifier: Programming Language :: Python :: 2
Classifier: Programming Language :: Python :: 2.7
Requires-Dist: peppercorn
